face_classifier/__init__.py
face_classifier/cli.py
face2_classifier-0.1.1.dist-info/AUTHORS.rst
face2_classifier-0.1.1.dist-info/LICENSE
face2_classifier-0.1.1.dist-info/METADATA
face2_classifier-0.1.1.dist-info/WHEEL
face2_classifier-0.1.1.dist-info/entry_points.txt
face2_classifier-0.1.1.dist-info/top_level.txt
face2_classifier-0.1.1.dist-info/RECORD
