Metadata-Version: 2.1
Name: face2-classifier
Version: 0.1.1
Summary: The facial classification tool base on face_recognition
Home-page: https://github.com/leviathan1995/face_classifier
Author: leviathan1995
Author-email: leviathan0992@gmail.com
License: MIT license
Keywords: face_classifier
Platform: UNKNOWN
Classifier: Development Status :: 2 - Pre-Alpha
Classifier: Intended Audience :: Developers
Classifier: License :: OSI Approved :: MIT License
Classifier: Natural Language :: English
Classifier: Programming Language :: Python :: 3
Classifier: Programming Language :: Python :: 3.5
Classifier: Programming Language :: Python :: 3.6
Classifier: Programming Language :: Python :: 3.7
Classifier: Programming Language :: Python :: 3.8
Requires-Python: >=3.5
Requires-Dist: Click (>=7.0)
